{
    "platform": {
        "depth_rating": "200m",
		"glider_type": "Teledyne Webb Research Slocum G2 glider",
		"id": "ru30",
		"instrument": "instrument_ctd,instrument_ph,instrument_flbbcd,instrument_optode",
		"long_name": "Slocum Glider ru30",
		"os_version": "8.5",
		"type": "platform",
		"wmo_id": "4801946"
    },
	"instrument_ctd": {
        "calibration_date": "2020-02-12",
		"comment": "Pumped",
		"factory_calibrated": "2020-02-12",
		"long_name": "Conductivity, Temperature, Depth (CTD) Sensor",
		"make_model": "Sea-Bird GPCTD",
		"platform": "platform",
		"serial_number": "9416",
		"type": "instrument"
    },
    "instrument_ph": {
        "calibration_date": "2020-03-06",
		"calibration_coefficients": " ",
		"comment": "V2",
		"factory_calibrated": "2020-03-06",
		"long_name": "Deep ISFET Ocean pH Sensor",
		"make_model": "Sea-Bird Deep ISFET Ocean pH Sensor",
		"platform": "platform",
		"serial_number": "10344",
		"type": "instrument"
    },
    "instrument_flbbcd": {
		"calibration_date": "2017-02-24",
		"comment": "Chlorophyll a,beta700nm,CDOM",
		"factory_calibrated": "2017-02-24",
		"long_name": "ECO Triplet Puck",
		"make_model": "Sea-Bird ECO Triplet flbbcdslc",
		"platform": "platform",
		"serial_number": "4662",
		"type": "instrument"
    },
    "instrument_optode": {
        "calibration_date": "2019-09-25",
		"factory_calibrated": "2019-09-25",
		"long_name": "Oxygen Optode",
		"make_model": "Aanderaa Oxygen Optode 4831",
		"platform": "platform",
		"serial_number": "242",
		"type": "instrument",
		"user_calibrated": "2020-02-03"
    },
    "trajectory": {
        "comment": "A trajectory is a single deployment of a glider. The trajectory for this deployment is",
		"ioos_category": "Identifier",
		"long_name": "Trajectory/Deployment Name"
    }
}
